[
  {
    "date": "2026-03-14",
    "title_zh": "Lanvin副总裁Sidhartha Shukla离职",
    "title_en": "Lanvin Deputy CEO Siddhartha Shukla Exits",
    "source": "Business of Fashion",
    "url": "https://www.businessoffashion.com/news/luxury/lanvin-deputy-ceo-siddhartha-shukla-exits-brand/",
    "category": "international"
  },
  {
    "date": "2026-03-14",
    "title_zh": "Prada任命Bella Hadid为首位全球美妆大使",
    "title_en": "Prada Appoints Bella Hadid as First Global Beauty Ambassador",
    "source": "FashionNetwork",
    "url": "https://ww.fashionnetwork.com/news/Prada-appoints-bella-hadid-as-first-global-beauty-ambassador,1815582.html",
    "category": "international"
  },
  {
    "date": "2026-03-14",
    "title_zh": "Vuori推出首个女士牛仔系列",
    "title_en": "Vuori Launches First Women's Denim Collection",
    "source": "FashionNetwork",
    "url": "https://ww.fashionnetwork.com/news/Vuori-launches-first-women-s-denim-collection,1815808.html",
    "category": "international"
  },
  {
    "date": "2026-03-14",
    "title_zh": "LV如何强化时装竞争力？",
    "title_en": "How LV Strengthens Fashion Competitiveness",
    "source": "时尚头条网",
    "url": "http://news.ladymax.cn/202603/13-39464.html",
    "category": "china"
  },
  {
    "date": "2026-03-14",
    "title_zh": "去年太古旗下内地全部商场销售额获得增长",
    "title_en": "Swire Properties All Mainland Malls Achieve Sales Growth",
    "source": "时尚头条网",
    "url": "http://news.ladymax.cn/202603/13-39463.html",
    "category": "china"
  },
  {
    "date": "2026-03-13",
    "title_zh": "LVMH任命Béatrice Goasglas为Tag Heuer新CEO",
    "title_en": "LVMH Names Béatrice Goasglas CEO of Tag Heuer",
    "source": "Business of Fashion",
    "url": "https://www.businessoffashion.com/articles/luxury/lvmh-names-beatrice-goasglas-ceo-of-tag-heuer/",
    "category": "international"
  },
  {
    "date": "2026-03-13",
    "title_zh": "Marco De Vincenzo离开Etro",
    "title_en": "Marco De Vincenzo Exits Etro",
    "source": "Business of Fashion",
    "url": "https://www.businessoffashion.com/news/luxury/marco-de-vincenzo-exits-etro/",
    "category": "international"
  },
  {
    "date": "2026-03-13",
    "title_zh": "Scotch & Soda与Basquiat联名系列上市",
    "title_en": "Scotch & Soda's Basquiat Capsule Hits Retail",
    "source": "WWD",
    "url": "https://wwd.com/fashion-news/fashion-scoops/scotch-amp-sodas-basquiat-capsule-bluestar-1238650892/",
    "category": "international"
  },
  {
    "date": "2026-03-13",
    "title_zh": "Prada集团2025年收入增长5%",
    "title_en": "Prada Group Closes 2025 With 5% Revenue Growth",
    "source": "WWD",
    "url": "https://wwd.com/business-news/financial/prada-group-2025-revenue-growth-miu-miu-outperform-1238649057/",
    "category": "international"
  },
  {
    "date": "2026-03-13",
    "title_zh": "维密关闭中国首家最大旗舰店",
    "title_en": "Victoria's Secret Closes Largest China Flagship",
    "source": "时尚头条网",
    "url": "http://news.ladymax.cn/202603/12-39462.html",
    "category": "china"
  },
  {
    "date": "2026-03-13",
    "title_zh": "The North Face全球品牌总裁离任",
    "title_en": "The North Face Global Brand President Steps Down",
    "source": "时尚头条网",
    "url": "http://news.ladymax.cn/202603/11-39460.html",
    "category": "china"
  }
]
